README.txt
setup.cfg
setup.py
docs/HISTORY.txt
docs/INSTALL.txt
docs/LICENSE.GPL
docs/LICENSE.txt
mfabrik/__init__.py
mfabrik.plonezohointegration.egg-info/PKG-INFO
mfabrik.plonezohointegration.egg-info/SOURCES.txt
mfabrik.plonezohointegration.egg-info/dependency_links.txt
mfabrik.plonezohointegration.egg-info/entry_points.txt
mfabrik.plonezohointegration.egg-info/namespace_packages.txt
mfabrik.plonezohointegration.egg-info/not-zip-safe
mfabrik.plonezohointegration.egg-info/paster_plugins.txt
mfabrik.plonezohointegration.egg-info/requires.txt
mfabrik.plonezohointegration.egg-info/top_level.txt
mfabrik/plonezohointegration/__init__.py
mfabrik/plonezohointegration/configure.zcml
mfabrik/plonezohointegration/i18n.sh
mfabrik/plonezohointegration/interfaces.py
mfabrik/plonezohointegration/tests.py
mfabrik/plonezohointegration/utils.py
mfabrik/plonezohointegration/views.py
mfabrik/plonezohointegration/locales/mfabrik.plonezohointegration.pot
mfabrik/plonezohointegration/locales/de/LC_MESSAGES/mfabrik.plonezohointegration.po
mfabrik/plonezohointegration/locales/en/LC_MESSAGES/mfabrik.plonezohointegration.po
mfabrik/plonezohointegration/locales/fi/LC_MESSAGES/mfabrik.plonezohointegration.po
mfabrik/plonezohointegration/locales/fr/LC_MESSAGES/mfabrik.plonezohointegration.po
mfabrik/plonezohointegration/portlets/__init__.py
mfabrik/plonezohointegration/portlets/configure.zcml
mfabrik/plonezohointegration/portlets/portletform.pt
mfabrik/plonezohointegration/portlets/zohocrmcontact.pt
mfabrik/plonezohointegration/portlets/zohocrmcontact.py
mfabrik/plonezohointegration/profiles/default/controlpanel.xml
mfabrik/plonezohointegration/profiles/default/metadata.xml
mfabrik/plonezohointegration/profiles/default/portlets.xml
mfabrik/plonezohointegration/profiles/default/registry.xml