Metadata-Version: 1.0
Name: mfabrik.plonezohointegration
Version: 0.1.2
Summary: Integration of Zoho web applications for Plone CMS
Home-page: http://webandmobile.mfabrik.com
Author: mFabrik Research Oy
Author-email: research@mfabrik.com
License: GPL
Keywords: zoho plone crm integration
Platform: UNKNOWN
Classifier: Framework :: Plone
Classifier: Programming Language :: Python
